jp_ndb_medicine/_.py
jp_ndb_medicine/__init__.py
jp_ndb_medicine-1.1.1.dist-info/licenses/LICENSE
jp_ndb_medicine-1.1.1.dist-info/METADATA
jp_ndb_medicine-1.1.1.dist-info/WHEEL
jp_ndb_medicine-1.1.1.dist-info/top_level.txt
jp_ndb_medicine-1.1.1.dist-info/RECORD
