Metadata-Version: 2.4
Name: jp_ndb_medicine
Version: 1.1.1
Summary: NDBオープンデータから、処方薬のデータを簡単に取得・利用するためのライブラリ
Author-email: SHIRO <shiro46mt@gmail.com>
License-Expression: MIT
Project-URL: Repository, https://github.com/shiro46mt/jp-ndb-medicine.git
Classifier: Development Status :: 5 - Production/Stable
Classifier: Programming Language :: Python :: 3
Classifier: Topic :: Scientific/Engineering :: Bio-Informatics
Classifier: Topic :: Scientific/Engineering :: Medical Science Apps.
Classifier: Natural Language :: Japanese
Requires-Python: >=3.8
License-File: LICENSE
Requires-Dist: beautifulsoup4
Requires-Dist: openpyxl
Requires-Dist: pandas
Requires-Dist: requests
Requires-Dist: tqdm
Requires-Dist: xlrd>=2.0.1
Dynamic: license-file
